{
  "info": {
    "_postman_id": "b6bce788-7480-4840-a047-66894144949a",
    "name": "TCC",
    "schema": "https://schema.getpostman.com/json/collection/v2.1.0/collection.json",
    "_exporter_id": "28609613"
  },
  "item": [
    {
      "name": "Customer",
      "item": [
        {
          "name": "Create Customer Account (sem token)",
          "request": {
            "method": "POST",
            "header": [],
            "body": {
              "mode": "raw",
              "raw": "{\n    \"name\": \"Pedro Teste\",\n    \"email\": \"pedro_cliente@gmail.com\",\n    \"password\": \"minhaSenha\",\n    \"phoneNumber\": \"31985105481\"\n}",
              "options": {
                "raw": {
                  "language": "json"
                }
              }
            },
            "url": {
              "raw": "http://localhost:8080/api/customers",
              "protocol": "http",
              "host": [
                "localhost"
              ],
              "port": "8080",
              "path": [
                "api",
                "customers"
              ]
            }
          },
          "response": []
        },
        {
          "name": "Get all Customer Account (Admin Only)",
          "request": {
            "method": "GET",
            "header": [
              {
                "key": "Authorization",
                "value": "Bearer {{token}}",
                "type": "text"
              }
            ],
            "url": {
              "raw": "http://localhost:8080/api/customers",
              "protocol": "http",
              "host": [
                "localhost"
              ],
              "port": "8080",
              "path": [
                "api",
                "customers"
              ]
            }
          },
          "response": []
        },
        {
          "name": "Get Customer (Customer Only)",
          "request": {
            "method": "GET",
            "header": [
              {
                "key": "Authorization",
                "value": "Bearer {{token}}",
                "type": "text"
              }
            ],
            "url": {
              "raw": "http://localhost:8080/api/customers/email",
              "protocol": "http",
              "host": [
                "localhost"
              ],
              "port": "8080",
              "path": [
                "api",
                "customers",
                "email"
              ]
            }
          },
          "response": []
        },
        {
          "name": "Update Customer Info (Customer Only)",
          "request": {
            "method": "PUT",
            "header": [
              {
                "key": "Authorization",
                "value": "Bearer {{token}}",
                "type": "text"
              }
            ],
            "body": {
              "mode": "raw",
              "raw": "{\r\n    \"email\": \"pedro_123@gmail.com\", // pode ser 1 de cada\r\n    \"password\": \"minhaSenha\",\r\n    \"phoneNumber\": \"31985105481\"\r\n}",
              "options": {
                "raw": {
                  "language": "json"
                }
              }
            },
            "url": {
              "raw": "http://localhost:8080/api/customers",
              "protocol": "http",
              "host": [
                "localhost"
              ],
              "port": "8080",
              "path": [
                "api",
                "customers"
              ]
            }
          },
          "response": []
        },
        {
          "name": "Delete Customer (Customer Only)",
          "request": {
            "method": "DELETE",
            "header": [
              {
                "key": "Authorization",
                "value": "Bearer {{token}}",
                "type": "text"
              }
            ],
            "url": {
              "raw": "http://localhost:8080/api/customers",
              "protocol": "http",
              "host": [
                "localhost"
              ],
              "port": "8080",
              "path": [
                "api",
                "customers"
              ]
            }
          },
          "response": []
        }
      ]
    },
    {
      "name": "Admin (Admin Only)",
      "item": [
        {
          "name": "Get Admin",
          "request": {
            "method": "GET",
            "header": [
              {
                "key": "Authorization",
                "value": "Bearer {{token}}",
                "type": "text"
              }
            ],
            "url": {
              "raw": "http://localhost:8080/api/admins",
              "protocol": "http",
              "host": [
                "localhost"
              ],
              "port": "8080",
              "path": [
                "api",
                "admins"
              ]
            }
          },
          "response": []
        },
        {
          "name": "Create Admin Account",
          "request": {
            "method": "POST",
            "header": [
              {
                "key": "Authorization",
                "value": "Bearer {{token}}",
                "type": "text"
              }
            ],
            "body": {
              "mode": "raw",
              "raw": "{\n    \"name\": \"Pedro Teste\",\n    \"email\": \"pedro_admin@gmail.com\",\n    \"password\": \"minhaSenha\",\n    \"phoneNumber\": \"31985105481\"\n}",
              "options": {
                "raw": {
                  "language": "json"
                }
              }
            },
            "url": {
              "raw": "http://localhost:8080/api/admins",
              "protocol": "http",
              "host": [
                "localhost"
              ],
              "port": "8080",
              "path": [
                "api",
                "admins"
              ]
            }
          },
          "response": []
        },
        {
          "name": "Update Admin Info",
          "request": {
            "method": "PUT",
            "header": [
              {
                "key": "Authorization",
                "value": "Bearer {{token}}",
                "type": "text"
              }
            ],
            "body": {
              "mode": "raw",
              "raw": "{\r\n    \"email\": \"pedro_12345555555555555@gmail.com\", // pode ser 1 de cada\r\n    \"password\": \"minhaSenha\",\r\n    \"phoneNumber\": \"31985105481\"\r\n}",
              "options": {
                "raw": {
                  "language": "json"
                }
              }
            },
            "url": {
              "raw": "http://localhost:8080/api/admins",
              "protocol": "http",
              "host": [
                "localhost"
              ],
              "port": "8080",
              "path": [
                "api",
                "admins"
              ]
            }
          },
          "response": []
        }
      ]
    },
    {
      "name": "Delivery Man",
      "item": [
        {
          "name": "Create Delivery Man Account (Admin Only)",
          "request": {
            "method": "POST",
            "header": [
              {
                "key": "Authorization",
                "value": "Bearer {{token}}",
                "type": "text"
              }
            ],
            "body": {
              "mode": "raw",
              "raw": "{\n    \"name\": \"Pedro Teste\",\n    \"email\": \"pedro_entregador@gmail.com\",\n    \"password\": \"minhaSenha\",\n    \"phoneNumber\": \"31985105481\"\n}",
              "options": {
                "raw": {
                  "language": "json"
                }
              }
            },
            "url": {
              "raw": "http://localhost:8080/api/delivery-men",
              "protocol": "http",
              "host": [
                "localhost"
              ],
              "port": "8080",
              "path": [
                "api",
                "delivery-men"
              ]
            }
          },
          "response": []
        },
        {
          "name": "Get All Delivery Man Account (Admin Only)",
          "request": {
            "method": "GET",
            "header": [
              {
                "key": "Authorization",
                "value": "Bearer {{token}}",
                "type": "text"
              }
            ],
            "url": {
              "raw": "http://localhost:8080/api/delivery-men",
              "protocol": "http",
              "host": [
                "localhost"
              ],
              "port": "8080",
              "path": [
                "api",
                "delivery-men"
              ]
            }
          },
          "response": []
        },
        {
          "name": "Update Admin Info By Id (Admin Only)",
          "request": {
            "method": "PUT",
            "header": [
              {
                "key": "Authorization",
                "value": "Bearer {{token}}",
                "type": "text"
              }
            ],
            "body": {
              "mode": "raw",
              "raw": "{\r\n    \"email\": \"pedro_1234888999988@gmail.com\",\r\n    \"password\": \"minhaSenha\",\r\n    \"phoneNumber\": \"31985105481\"\r\n}",
              "options": {
                "raw": {
                  "language": "json"
                }
              }
            },
            "url": {
              "raw": "http://localhost:8080/api/delivery-men/{{delivery_man_id}}",
              "protocol": "http",
              "host": [
                "localhost"
              ],
              "port": "8080",
              "path": [
                "api",
                "delivery-men",
                "{{delivery_man_id}}"
              ]
            }
          },
          "response": []
        },
        {
          "name": "Delete Admin By Id (Admin Only)",
          "request": {
            "method": "DELETE",
            "header": [
              {
                "key": "Authorization",
                "value": "Bearer {{token}}",
                "type": "text"
              }
            ],
            "url": {
              "raw": "http://localhost:8080/api/delivery-men/{{delivery_man_id}}",
              "protocol": "http",
              "host": [
                "localhost"
              ],
              "port": "8080",
              "path": [
                "api",
                "delivery-men",
                "{{delivery_man_id}}"
              ]
            }
          },
          "response": []
        },
        {
          "name": "Get Delivery Man (Delivery Only)",
          "request": {
            "method": "GET",
            "header": [
              {
                "key": "Authorization",
                "value": "Bearer {{token}}",
                "type": "text"
              }
            ],
            "url": {
              "raw": "http://localhost:8080/api/delivery-men/email",
              "protocol": "http",
              "host": [
                "localhost"
              ],
              "port": "8080",
              "path": [
                "api",
                "delivery-men",
                "email"
              ]
            }
          },
          "response": []
        }
      ]
    },
    {
      "name": "Order",
      "item": [
        {
          "name": "create order (Customer Only)",
          "request": {
            "method": "POST",
            "header": [
              {
                "key": "Authorization",
                "value": "Bearer {{token}}",
                "type": "text"
              }
            ],
            "body": {
              "mode": "raw",
              "raw": "{\n    \"description\": \"pedido teste\",\n    \"observation\": \"observation\",\n    \"address\": {\n        \"street\": \"Rua teste\",\n        \"number\": \"55\",\n        \"neighborhood\": \"Bairro Joao\",\n        \"zipCode\": \"55555-000\",\n        \"complement\": \"teste\"\n    }\n}",
              "options": {
                "raw": {
                  "language": "json"
                }
              }
            },
            "url": {
              "raw": "http://localhost:8080/api/orders",
              "protocol": "http",
              "host": [
                "localhost"
              ],
              "port": "8080",
              "path": [
                "api",
                "orders"
              ]
            }
          },
          "response": []
        },
        {
          "name": "get all orders (Admin Only)",
          "request": {
            "method": "GET",
            "header": [
              {
                "key": "Authorization",
                "value": "Bearer {{token}}",
                "type": "text"
              }
            ],
            "url": {
              "raw": "http://localhost:8080/api/orders",
              "protocol": "http",
              "host": [
                "localhost"
              ],
              "port": "8080",
              "path": [
                "api",
                "orders"
              ]
            }
          },
          "response": []
        },
        {
          "name": "Get Order Of Customer (Customer Only)",
          "request": {
            "method": "GET",
            "header": [
              {
                "key": "Authorization",
                "value": "Bearer {{token}}",
                "type": "text"
              }
            ],
            "url": {
              "raw": "http://localhost:8080/api/orders/customer",
              "protocol": "http",
              "host": [
                "localhost"
              ],
              "port": "8080",
              "path": [
                "api",
                "orders",
                "customer"
              ]
            }
          },
          "response": []
        },
        {
          "name": "Get Order Of Delivery Man (Delivery Only)",
          "request": {
            "method": "GET",
            "header": [
              {
                "key": "Authorization",
                "value": "Bearer {{token}}",
                "type": "text"
              }
            ],
            "url": {
              "raw": "http://localhost:8080/api/orders/delivery-man",
              "protocol": "http",
              "host": [
                "localhost"
              ],
              "port": "8080",
              "path": [
                "api",
                "orders",
                "delivery-man"
              ]
            }
          },
          "response": []
        },
        {
          "name": "Get Order from Customer Id (Admin only)",
          "request": {
            "method": "GET",
            "header": [
              {
                "key": "Authorization",
                "value": "Bearer {{token}}",
                "type": "text"
              }
            ],
            "url": {
              "raw": "http://localhost:8080/api/orders/customer/{{customer_id}}",
              "protocol": "http",
              "host": [
                "localhost"
              ],
              "port": "8080",
              "path": [
                "api",
                "orders",
                "customer",
                "{{customer_id}}"
              ]
            }
          },
          "response": []
        },
        {
          "name": "Get Order from Delivery Man (Admin Only)",
          "request": {
            "method": "GET",
            "header": [
              {
                "key": "Authorization",
                "value": "Bearer {{token}}",
                "type": "text"
              }
            ],
            "url": {
              "raw": "http://localhost:8080/api/orders/delivery-man/{{delivery_man_id}}",
              "protocol": "http",
              "host": [
                "localhost"
              ],
              "port": "8080",
              "path": [
                "api",
                "orders",
                "delivery-man",
                "{{delivery_man_id}}"
              ]
            }
          },
          "response": []
        },
        {
          "name": "Assign Order By Id",
          "request": {
            "method": "PUT",
            "header": [
              {
                "key": "Authorization",
                "value": "Bearer {{token}}",
                "type": "text"
              }
            ],
            "body": {
              "mode": "raw",
              "raw": "{\r\n    \"deliveryManId\": \"2\"\r\n}",
              "options": {
                "raw": {
                  "language": "json"
                }
              }
            },
            "url": {
              "raw": "http://localhost:8080/api/orders/{{order_id}}/assign",
              "protocol": "http",
              "host": [
                "localhost"
              ],
              "port": "8080",
              "path": [
                "api",
                "orders",
                "{{order_id}}",
                "assign"
              ]
            }
          },
          "response": []
        },
        {
          "name": "Update Order Status By Delivery (Delivery Only)",
          "request": {
            "method": "PUT",
            "header": [
              {
                "key": "Authorization",
                "value": "Bearer {{token}}",
                "type": "text"
              }
            ],
            "body": {
              "mode": "raw",
              "raw": "{\r\n    \"status\": \"IN_TRANSIT\"\r\n}",
              "options": {
                "raw": {
                  "language": "json"
                }
              }
            },
            "url": {
              "raw": "http://localhost:8080/api/orders/delivery-man/{{order_id}}/status",
              "protocol": "http",
              "host": [
                "localhost"
              ],
              "port": "8080",
              "path": [
                "api",
                "orders",
                "delivery-man",
                "{{order_id}}",
                "status"
              ]
            }
          },
          "response": []
        }
      ]
    },
    {
      "name": "Login",
      "item": [
        {
          "name": "get token - admin",
          "event": [
            {
              "listen": "test",
              "script": {
                "exec": [
                  "pm.test(\"Status code is 200\", function () {\r",
                  "    pm.response.to.have.status(200);\r",
                  "});\r",
                  "\r",
                  "let jsonData = pm.response.json();\r",
                  "const token = jsonData.token;\r",
                  "\r",
                  "pm.collectionVariables.set(\"token\", token);"
                ],
                "type": "text/javascript",
                "packages": {},
                "requests": {}
              }
            }
          ],
          "request": {
            "method": "POST",
            "header": [],
            "body": {
              "mode": "raw",
              "raw": "{\r\n    \"email\": \"teste_admin@rapidoja.com\",\r\n    \"password\": \"admin123\"\r\n}",
              "options": {
                "raw": {
                  "language": "json"
                }
              }
            },
            "url": {
              "raw": "http://localhost:8080/api/auth/login",
              "protocol": "http",
              "host": [
                "localhost"
              ],
              "port": "8080",
              "path": [
                "api",
                "auth",
                "login"
              ]
            }
          },
          "response": []
        },
        {
          "name": "get token - customer",
          "event": [
            {
              "listen": "test",
              "script": {
                "exec": [
                  "pm.test(\"Status code is 200\", function () {\r",
                  "    pm.response.to.have.status(200);\r",
                  "});\r",
                  "\r",
                  "let jsonData = pm.response.json();\r",
                  "const token = jsonData.token;\r",
                  "\r",
                  "pm.collectionVariables.set(\"token\", token);"
                ],
                "type": "text/javascript",
                "packages": {},
                "requests": {}
              }
            }
          ],
          "request": {
            "method": "POST",
            "header": [],
            "body": {
              "mode": "raw",
              "raw": "{\r\n    \"email\": \"joao_cliente@email.com\",\r\n    \"password\": \"admin123\"\r\n}",
              "options": {
                "raw": {
                  "language": "json"
                }
              }
            },
            "url": {
              "raw": "http://localhost:8080/api/auth/login",
              "protocol": "http",
              "host": [
                "localhost"
              ],
              "port": "8080",
              "path": [
                "api",
                "auth",
                "login"
              ]
            }
          },
          "response": []
        },
        {
          "name": "get token - delivery",
          "event": [
            {
              "listen": "test",
              "script": {
                "exec": [
                  "pm.test(\"Status code is 200\", function () {\r",
                  "    pm.response.to.have.status(200);\r",
                  "});\r",
                  "\r",
                  "let jsonData = pm.response.json();\r",
                  "const token = jsonData.token;\r",
                  "\r",
                  "pm.collectionVariables.set(\"token\", token);"
                ],
                "type": "text/javascript",
                "packages": {},
                "requests": {}
              }
            }
          ],
          "request": {
            "method": "POST",
            "header": [],
            "body": {
              "mode": "raw",
              "raw": "{\r\n    \"email\": \"maria_entregadora@email.com\",\r\n    \"password\": \"admin123\"\r\n}",
              "options": {
                "raw": {
                  "language": "json"
                }
              }
            },
            "url": {
              "raw": "http://localhost:8080/api/auth/login",
              "protocol": "http",
              "host": [
                "localhost"
              ],
              "port": "8080",
              "path": [
                "api",
                "auth",
                "login"
              ]
            }
          },
          "response": []
        }
      ]
    }
  ],
  "variable": [
    {
      "key": "id",
      "value": ""
    },
    {
      "key": "email",
      "value": ""
    },
    {
      "key": "token",
      "value": ""
    },
    {
      "key": "order_id",
      "value": ""
    },
    {
      "key": "customer_id",
      "value": ""
    },
    {
      "key": "customer_email",
      "value": ""
    },
    {
      "key": "delivery_man_id",
      "value": ""
    },
    {
      "key": "delivery_man_email",
      "value": ""
    },
    {
      "key": "status_order",
      "value": ""
    }
  ]
}